azureml/dataprep/native.cpython-310-x86_64-linux-gnu.so
azureml_dataprep_native-42.1.0.dist-info/licenses/LICENSE.txt
azureml_dataprep_native-42.1.0.dist-info/METADATA
azureml_dataprep_native-42.1.0.dist-info/WHEEL
azureml_dataprep_native-42.1.0.dist-info/top_level.txt
azureml_dataprep_native-42.1.0.dist-info/RECORD
